data_aggregator_sdk/__init__.py
data_aggregator_sdk/dag.yml
data_aggregator_sdk/data_aggregator_api_sdk.py
data_aggregator_sdk/data_aggregator_api_sdk_config.py
data_aggregator_sdk/data_aggregator_sdk.py
data_aggregator_sdk/data_aggregator_sdk_config.py
data_aggregator_sdk/errors.py
data_aggregator_sdk/integration_message.py
data_aggregator_sdk/lib.py
data_aggregator_sdk/py.typed
data_aggregator_sdk/runtime_conf.py
data_aggregator_sdk/self_logging.py
data_aggregator_sdk/__tests__/__init__.py
data_aggregator_sdk/__tests__/test_integration_message.py
data_aggregator_sdk/brokers/__init__.py
data_aggregator_sdk/brokers/data_aggregator_input_broker.py
data_aggregator_sdk/constants/__init__.py
data_aggregator_sdk/constants/annotations.py
data_aggregator_sdk/constants/clock_timezones.py
data_aggregator_sdk/constants/enums.py
data_aggregator_sdk/constants/names.py
data_aggregator_sdk/types/__init__.py
data_aggregator_sdk/types/device.py
data_aggregator_sdk/types/get_data_gateway_network_device_list.py
data_aggregator_sdk/utils/__init__.py
data_aggregator_sdk/utils/devices_info_box_to_json.py
data_aggregator_sdk/utils/internal_api_error_handler.py
data_aggregator_sdk/utils/internal_api_error_handler_old.py
data_aggregator_sdk/utils/query_params.py
data_aggregator_sdk/utils/round_dt.py
ul_data_aggregator_sdk-11.0.0.dist-info/METADATA
ul_data_aggregator_sdk-11.0.0.dist-info/WHEEL
ul_data_aggregator_sdk-11.0.0.dist-info/top_level.txt
ul_data_aggregator_sdk-11.0.0.dist-info/RECORD
